fem/__init__.py
fem.py-0.0.1.dist-info/WHEEL
fem.py-0.0.1.dist-info/METADATA
fem.py-0.0.1.dist-info/RECORD
