Metadata-Version: 2.1
Name: fem.py
Version: 0.0.1
Summary: 
Author: Tiago Vilela
Author-email: tiagovla@gmail.com
Requires-Python: >=3.8,<4.0
Classifier: Programming Language :: Python :: 3
Classifier: Programming Language :: Python :: 3.8
Classifier: Programming Language :: Python :: 3.9
Requires-Dist: numpy (>=1.20.1,<2.0.0)
